makeqr/__init__.py
makeqr/__main__.py
makeqr/cli_app.py
makeqr/constants.py
makeqr/makeqr.py
makeqr/models.py
makeqr/typing.py
makeqr/utils.py
makeqr/version.py
makeqr-4.4.1.dist-info/METADATA
makeqr-4.4.1.dist-info/WHEEL
makeqr-4.4.1.dist-info/entry_points.txt
makeqr-4.4.1.dist-info/RECORD
