Metadata-Version: 2.1
Name: MakeQR
Version: 4.4.1
Summary: Generate QR cards for any occasion
Home-page: https://github.com/shpaker/makeqr
Author: Aleksandr Shpak
Author-email: shpaker@gmail.com
Requires-Python: >=3.9,<4.0.0
Classifier: License :: OSI Approved :: MIT License
Classifier: Operating System :: OS Independent
Classifier: Programming Language :: Python :: 3
Classifier: Programming Language :: Python :: 3.9
Classifier: Programming Language :: Python :: 3.10
Classifier: Programming Language :: Python :: 3.11
Classifier: Programming Language :: Python :: 3.12
Requires-Dist: click (>=8.1)
Requires-Dist: pydantic[email] (>=2.0)
Requires-Dist: qrcode[pil] (>=7.0)
Project-URL: Repository, https://github.com/shpaker/makeqr
